LICENSE
README.md
setup.py
constructor_io/__init__.py
constructor_io/constructor_io.py
constructor_io.egg-info/PKG-INFO
constructor_io.egg-info/SOURCES.txt
constructor_io.egg-info/dependency_links.txt
constructor_io.egg-info/requires.txt
constructor_io.egg-info/top_level.txt
constructor_io/helpers/__init__.py
constructor_io/helpers/exception.py
constructor_io/helpers/utils.py
constructor_io/modules/__init__.py
constructor_io/modules/autocomplete.py
constructor_io/modules/browse.py
constructor_io/modules/catalog.py
constructor_io/modules/quizzes.py
constructor_io/modules/recommendations.py
constructor_io/modules/search.py
constructor_io/modules/tasks.py