Metadata-Version: 2.1
Name: constructor-io
Version: 1.8.7
Summary: Constructor.io Python Client
Home-page: https://www.constructor.io
Author: Constructor.io Corporation
Author-email: info@constructor.io
License: MIT
Download-URL: https://github.com/Constructor-io/constructor-io/tarball/1.8.7
Platform: UNKNOWN
License-File: LICENSE
